pulib/__init__.py
pulib/pu_data.py
pulib-1.0.4.dist-info/METADATA
pulib-1.0.4.dist-info/RECORD
pulib-1.0.4.dist-info/WHEEL
pulib-1.0.4.dist-info/top_level.txt
