Metadata-Version: 2.1
Name: pulib
Version: 1.0.4
Summary: Positive-Unlabeled machine learning package
Home-page: https://github.com/ronaldpereira/pulib
Author: Ronald Pereira
Author-email: ronald.drp11@gmail.com
License: UNKNOWN
Platform: UNKNOWN
Classifier: Programming Language :: Python :: 3
Classifier: License :: OSI Approved :: GNU General Public License v3 (GPLv3)
Classifier: Operating System :: OS Independent
